modelbest_data/__init__.py
modelbest_data/file_format/__init__.py
modelbest_data/file_format/mbtable.py
modelbest_data/file_format/mbtable_builder.py
modelbest_data/file_format/mbtable_partition.py
modelbest_data/file_format/lib/libsstable_sdk_shared.so
test/__init__.py
test/test_mbtable.py
test/test_mbtable_partition.py
modelbest_data-0.0.7.dist-info/METADATA
modelbest_data-0.0.7.dist-info/WHEEL
modelbest_data-0.0.7.dist-info/top_level.txt
modelbest_data-0.0.7.dist-info/RECORD
